pysyringe/__init__.py
pysyringe/container.py
pysyringe/singleton.py
pysyringe-1.2.1.dist-info/METADATA
pysyringe-1.2.1.dist-info/WHEEL
pysyringe-1.2.1.dist-info/licenses/LICENSE
pysyringe-1.2.1.dist-info/RECORD
