Metadata-Version: 2.4
Name: pysyringe
Version: 1.2.1
Summary: An opinionated dependency injection library for Python
Project-URL: homepage, https://github.com/hugochinchilla/pysyringe
Project-URL: repository, https://github.com/hugochinchilla/pysyringe
Project-URL: issues, https://github.com/hugochinchilla/pysyringe/issues
Author-email: Hugo Chinchilla <hugoasecas@gmail.com>
License: MIT
License-File: LICENSE
Requires-Python: <3.13,>=3.12
